brainio/__init__.py
brainio/brainio.py
brainio/utils.py
tests/__init__.py
tests/tests/__init__.py
tests/tests/test_brainio.py
brainio-0.0.20.dist-info/LICENSE
brainio-0.0.20.dist-info/METADATA
brainio-0.0.20.dist-info/WHEEL
brainio-0.0.20.dist-info/top_level.txt
brainio-0.0.20.dist-info/RECORD
