Metadata-Version: 2.1
Name: brainio
Version: 0.0.20
Summary: Loading and saving of brain imaging data.
Home-page: https://github.com/adamltyson/brainio
Author: Adam Tyson, Charly Rousseau
Author-email: adam.tyson@ucl.ac.uk
License: UNKNOWN
Platform: UNKNOWN
Classifier: Development Status :: 3 - Alpha
Classifier: Operating System :: POSIX :: Linux
Classifier: Operating System :: Microsoft :: Windows :: Windows 10
Classifier: Programming Language :: Python
Classifier: Programming Language :: Python :: 3.6
Classifier: Programming Language :: Python :: 3.7
Classifier: Programming Language :: Python :: 3.8
Classifier: Intended Audience :: Developers
Classifier: Intended Audience :: Science/Research
Requires-Python: >=3.6
Requires-Dist: numpy
Requires-Dist: scikit-image
Requires-Dist: tifffile
Requires-Dist: pynrrd
Requires-Dist: nibabel
Requires-Dist: tqdm
Requires-Dist: natsort
Requires-Dist: psutil
Requires-Dist: slurmio (>=0.0.5)
Requires-Dist: imlib
Requires-Dist: nibabel (>=2.1.0)
Provides-Extra: dev
Requires-Dist: black ; extra == 'dev'
Requires-Dist: pytest-cov ; extra == 'dev'
Requires-Dist: pytest ; extra == 'dev'
Requires-Dist: coverage ; extra == 'dev'
